<instance version="6" description="" template="ebps">
	<list name="extensions">
		<template_reference name="exts" value="ebpextensions\type_ext" List.ItemID="1432368975" List.ParentItemID="1432368975">
			<list name="race_type_list" overrideParent="True">
				<instance_reference name="race_type" value="racebps\campaign_xp3\crusader_cmp" overrideParent="True" List.ItemID="-1268095300" />
			</list>
		</template_reference>
	</list>
	<uniqueid name="pbgid" value="2089040" />
	<instance_reference name="parent_pbg" value="ebps\races\french\buildings\building_resource_farm_fre\building_resource_farm_fre" />
	<variant name="xp3">
		<list name="extensions">
			<template_reference name="exts" value="ebpextensions\type_ext" List.ItemID="1432368975" List.ParentItemID="1432368975">
				<list name="race_type_list" overrideParent="True">
					<instance_reference name="race_type" value="racebps\campaign_xp3\crusader_cmp" overrideParent="True" List.ItemID="1029546815" />
				</list>
			</template_reference>
		</list>
		<uniqueid name="pbgid" value="2089040" />
		<instance_reference name="parent_pbg" value="ebps\races\french\buildings\building_resource_farm_fre\building_resource_farm_fre" />
	</variant>
</instance>